README.md
setup.py
NASGrpcFileSystem/__init__.py
NASGrpcFileSystem/code_dict.py
NASGrpcFileSystem/grpc_copy_move_file.py
NASGrpcFileSystem/grpc_create_file.py
NASGrpcFileSystem/grpc_describe_file.py
NASGrpcFileSystem/grpc_file_handle.py
NASGrpcFileSystem/grpc_modify_file.py
NASGrpcFileSystem/grpc_options.py
NASGrpcFileSystem.egg-info/PKG-INFO
NASGrpcFileSystem.egg-info/SOURCES.txt
NASGrpcFileSystem.egg-info/dependency_links.txt
NASGrpcFileSystem.egg-info/requires.txt
NASGrpcFileSystem.egg-info/top_level.txt
NASGrpcFileSystem/proto/__init__.py
NASGrpcFileSystem/proto/files_pb2.py
NASGrpcFileSystem/proto/files_pb2_grpc.py